neuralcoref/__init__.py
neuralcoref/file_utils.py
neuralcoref/neuralcoref.cpython-37m-darwin.so
neuralcoref/tests/__init__.py
neuralcoref/tests/test_neuralcoref.py
neuralcoref/train/__init__.py
neuralcoref/train/algorithm.py
neuralcoref/train/compat.py
neuralcoref/train/conllparser.py
neuralcoref/train/dataset.py
neuralcoref/train/document.py
neuralcoref/train/evaluator.py
neuralcoref/train/learn.py
neuralcoref/train/model.py
neuralcoref/train/utils.py
wneuralcoref-4.0.2.3.2.dist-info/LICENSE.txt
wneuralcoref-4.0.2.3.2.dist-info/METADATA
wneuralcoref-4.0.2.3.2.dist-info/WHEEL
wneuralcoref-4.0.2.3.2.dist-info/top_level.txt
wneuralcoref-4.0.2.3.2.dist-info/RECORD
