Metadata-Version: 2.1
Name: wneuralcoref
Version: 4.0.2.3.2
Summary: Coreference Resolution in spaCy with Neural Networks
Home-page: https://github.com/huggingface/neuralcoref
Author: Thomas Wolf
Author-email: thomwolf@gmail.com
License: MIT
Keywords: NLP chatbots coreference resolution
Platform: any
Classifier: Development Status :: 3 - Alpha
Classifier: Environment :: Console
Classifier: Intended Audience :: Developers
Classifier: Intended Audience :: Science/Research
Classifier: License :: OSI Approved :: MIT License
Classifier: Operating System :: POSIX :: Linux
Classifier: Operating System :: MacOS :: MacOS X
Classifier: Operating System :: Microsoft :: Windows
Classifier: Programming Language :: Cython
Classifier: Programming Language :: Python :: 3.6
Classifier: Programming Language :: Python :: 3.7
Classifier: Programming Language :: Python :: 3.8
Classifier: Topic :: Scientific/Engineering
Requires-Python: >=3.6
Requires-Dist: numpy (>=1.15.0)
Requires-Dist: boto3
Requires-Dist: requests (<3.0.0,>=2.13.0)
Requires-Dist: spacy (==2.3.2)
